{
  "epoch": 9,
  "mode": "proto",
  "train": {
    "acc": 0.4140570633263744,
    "mse": 0.005896408694466975,
    "n_free": 1437,
    "n_clamp": 1437,
    "skipped": 0,
    "reload_free": 0,
    "reload_clamp": 0,
    "nonfinite_free": 0,
    "nonfinite_clamp": 0
  },
  "val": {
    "acc": 0.4,
    "mse": 0.00577582730352717,
    "val_mode": "proto",
    "val_reloads": 0.0,
    "val_nonfinite": 0.0,
    "val_mse_count": 360.0
  },
  "timing_s": {
    "epoch_total": 90.06726932525635,
    "train_free": 32.981825828552246,
    "train_clamp": 33.41388010978699,
    "train_update": 4.153037071228027
  }
}