{
  "epoch": 79,
  "config": {
    "seed": 1,
    "gamma": 0.3,
    "margin": 0.1,
    "delta": 0.05,
    "input_vmin": 0.0,
    "input_vmax": 1.0,
    "rails": [
      0.0,
      0.45
    ],
    "solver": "klu",
    "body_tie": "floating",
    "body_res": 10.0,
    "rs_clamp": 10.0,
    "model_vto": 0.75,
    "vg_cutoff": 0.75,
    "vg_cutoff_epochs": 4,
    "vg_init": {
      "mode": "fixed",
      "lo": 1.0,
      "hi": 3.0,
      "fixed": 2.0
    },
    "epochs": 100,
    "device_include_path": "/home/ma-lab/Desktop/pyclln-final/device_model/nmos_lvl1_ald1106.lib",
    "device_subckt": "NMOSWRAP"
  },
  "train": {
    "acc": 0.9589422407794015,
    "hinge": 0.014655286708420331,
    "n_free": 1437,
    "n_clamp": 404,
    "hinge_active": 404,
    "hinge_active_frac": 0.28114126652748783,
    "skipped": 1033,
    "reload_free": 0,
    "reload_clamp": 0,
    "nonfinite_free": 0,
    "nonfinite_clamp": 0
  },
  "val": {
    "acc": 0.9305555555555556,
    "hinge": 0.017758075833333345,
    "test_gap_mean": 0.13269257916666666,
    "test_gap_median": 0.1417525,
    "test_gap_std": 0.07686613960548404,
    "test_satisfy_frac": 0.6944444444444444,
    "test_hinge_mean": 0.017758075833333335,
    "val_reloads": 0.0,
    "val_nonfinite": 0.0
  },
  "timing_s": {
    "epoch_total": 23.75632095336914,
    "train_free": 12.620316982269287,
    "train_clamp": 3.526188611984253,
    "train_update": 0.3972165584564209
  },
  "vg_stats": {
    "vg_unique_min": 0.7201946833330701,
    "vg_unique_max": 4.7023974181064325,
    "vg_unique_sat_lo": 0.0,
    "vg_unique_sat_hi": 0.0
  }
}