{
  "epoch": 83,
  "config": {
    "seed": 2,
    "gamma": 0.03,
    "margin": 0.1,
    "delta": 0.05,
    "input_vmin": 0.0,
    "input_vmax": 1.0,
    "rails": [
      0.0,
      0.45
    ],
    "solver": "klu",
    "body_tie": "source",
    "body_res": 10.0,
    "rs_clamp": 10.0,
    "model_vto": 0.75,
    "vg_cutoff": 0.75,
    "vg_cutoff_epochs": 4,
    "vg_init": {
      "mode": "fixed",
      "lo": 1.0,
      "hi": 3.0,
      "fixed": 2.0
    },
    "epochs": 100,
    "device_include_path": "/home/ma-lab/Desktop/pyclln-final/device_model/nmos_lvl1_ald1106.lib",
    "device_subckt": "NMOSWRAP"
  },
  "train": {
    "acc": 0.9283228949199722,
    "hinge": 0.036502686847599136,
    "n_free": 1437,
    "n_clamp": 1039,
    "hinge_active": 1039,
    "hinge_active_frac": 0.7230340988169798,
    "skipped": 398,
    "reload_free": 0,
    "reload_clamp": 0,
    "nonfinite_free": 0,
    "nonfinite_clamp": 0
  },
  "val": {
    "acc": 0.925,
    "hinge": 0.0380336852777778,
    "test_gap_mean": 0.0686971275,
    "test_gap_median": 0.07304664999999999,
    "test_gap_std": 0.04740247049532269,
    "test_satisfy_frac": 0.3055555555555556,
    "test_hinge_mean": 0.038033685277777785,
    "val_reloads": 0.0,
    "val_nonfinite": 0.0
  },
  "timing_s": {
    "epoch_total": 81.38991212844849,
    "train_free": 36.41795206069946,
    "train_clamp": 26.09079933166504,
    "train_update": 2.4744601249694824
  },
  "vg_stats": {
    "vg_unique_min": 0.667448303244849,
    "vg_unique_max": 4.154709902994882,
    "vg_unique_sat_lo": 0.0,
    "vg_unique_sat_hi": 0.0
  }
}