{
  "epoch": 19,
  "config": {
    "seed": 0,
    "gamma": 0.03,
    "margin": 0.05,
    "delta": 0.05,
    "input_vmin": 0.0,
    "input_vmax": 1.0,
    "rails": [
      0.0,
      0.45
    ],
    "solver": "klu",
    "body_tie": "source",
    "body_res": 10.0,
    "rs_clamp": 10.0,
    "model_vto": 0.75,
    "vg_cutoff": 0.75,
    "vg_cutoff_epochs": 4,
    "vg_init": {
      "mode": "random",
      "lo": 1.0,
      "hi": 6.0,
      "fixed": 2.0
    },
    "epochs": 100,
    "device_include_path": "/home/ma-lab/Desktop/pyclln-final/device_model/nmos_lvl1_ald1106.lib",
    "device_subckt": "NMOSWRAP"
  },
  "train": {
    "acc": 0.5490605427974948,
    "hinge": 0.047763777870563705,
    "n_free": 1437,
    "n_clamp": 1436,
    "hinge_active": 1436,
    "hinge_active_frac": 0.9993041057759221,
    "skipped": 1,
    "reload_free": 0,
    "reload_clamp": 0,
    "nonfinite_free": 0,
    "nonfinite_clamp": 0
  },
  "val": {
    "acc": 0.5666666666666667,
    "hinge": 0.0468112772222223,
    "test_gap_mean": 0.0031887227777777773,
    "test_gap_median": 0.003479849999999979,
    "test_gap_std": 0.019397886040569617,
    "test_satisfy_frac": 0.0,
    "test_hinge_mean": 0.04681127722222222,
    "val_reloads": 0.0,
    "val_nonfinite": 0.0
  },
  "timing_s": {
    "epoch_total": 103.4971432685852,
    "train_free": 38.15540599822998,
    "train_clamp": 39.3602819442749,
    "train_update": 4.103839635848999
  },
  "vg_stats": {
    "vg_unique_min": 0.6297958890895631,
    "vg_unique_max": 6.744610383256802,
    "vg_unique_sat_lo": 0.0,
    "vg_unique_sat_hi": 0.0
  }
}