{
  "epoch": 4,
  "config": {
    "seed": 0,
    "gamma": 0.03,
    "margin": 0.02,
    "delta": 0.02,
    "input_vmin": 0.0,
    "input_vmax": 1.0,
    "rails": [
      0.0,
      0.45
    ],
    "solver": "klu",
    "body_tie": "floating",
    "body_res": 10.0,
    "rs_clamp": 10.0,
    "model_vto": 0.75,
    "vg_cutoff": 0.75,
    "vg_cutoff_epochs": 4,
    "vg_init": {
      "mode": "random",
      "lo": 1.0,
      "hi": 6.0,
      "fixed": 2.0
    },
    "epochs": 100,
    "device_include_path": "/home/ma-lab/Desktop/pyclln-final/device_model/nmos_lvl1_ald1106.lib",
    "device_subckt": "NMOSWRAP"
  },
  "train": {
    "acc": 0.23312456506610996,
    "hinge": 0.042826380723729976,
    "n_free": 1437,
    "n_clamp": 1413,
    "hinge_active": 1413,
    "hinge_active_frac": 0.9832985386221295,
    "skipped": 24,
    "reload_free": 0,
    "reload_clamp": 0,
    "nonfinite_free": 0,
    "nonfinite_clamp": 0
  },
  "val": {
    "acc": 0.25555555555555554,
    "hinge": 0.041119781111111114,
    "test_gap_mean": -0.021020609166666666,
    "test_gap_median": -0.017212599999999995,
    "test_gap_std": 0.02846316030400328,
    "test_satisfy_frac": 0.030555555555555555,
    "test_hinge_mean": 0.041119781111111114,
    "val_reloads": 0.0,
    "val_nonfinite": 0.0
  },
  "timing_s": {
    "epoch_total": 299.13994216918945,
    "train_free": 130.43415141105652,
    "train_clamp": 128.40769124031067,
    "train_update": 3.6473166942596436
  },
  "vg_stats": {
    "vg_unique_min": 0.9786455187947822,
    "vg_unique_max": 6.111413494248409,
    "vg_unique_sat_lo": 0.0,
    "vg_unique_sat_hi": 0.0
  }
}