{
  "epoch": 73,
  "config": {
    "seed": 2,
    "gamma": 3.0,
    "margin": 0.02,
    "delta": 0.1,
    "input_vmin": 0.0,
    "input_vmax": 1.0,
    "rails": [
      0.0,
      0.45
    ],
    "solver": "klu",
    "body_tie": "source",
    "body_res": 10.0,
    "rs_clamp": 10.0,
    "model_vto": 0.75,
    "vg_cutoff": 0.75,
    "vg_cutoff_epochs": 4,
    "vg_init": {
      "mode": "random",
      "lo": 1.5,
      "hi": 2.5,
      "fixed": 2.0
    },
    "epochs": 100,
    "device_include_path": "/home/ma-lab/Desktop/pyclln-final/device_model/nmos_lvl1_ald1106.lib",
    "device_subckt": "NMOSWRAP"
  },
  "train": {
    "acc": 0.9596381350034795,
    "hinge": 0.002134645720250522,
    "n_free": 1437,
    "n_clamp": 125,
    "hinge_active": 125,
    "hinge_active_frac": 0.08698677800974251,
    "skipped": 1312,
    "reload_free": 0,
    "reload_clamp": 0,
    "nonfinite_free": 0,
    "nonfinite_clamp": 0
  },
  "val": {
    "acc": 0.95,
    "hinge": 0.0034898755555555537,
    "test_gap_mean": 0.09246508083333332,
    "test_gap_median": 0.09392484999999998,
    "test_gap_std": 0.0596950283084892,
    "test_satisfy_frac": 0.8861111111111111,
    "test_hinge_mean": 0.0034898755555555555,
    "val_reloads": 0.0,
    "val_nonfinite": 0.0
  },
  "timing_s": {
    "epoch_total": 13.65644359588623,
    "train_free": 7.833547592163086,
    "train_clamp": 0.6838648319244385,
    "train_update": 0.1182413101196289
  },
  "vg_stats": {
    "vg_unique_min": 0.4,
    "vg_unique_max": 6.065884231899093,
    "vg_unique_sat_lo": 1.0,
    "vg_unique_sat_hi": 0.0
  }
}