{
  "epoch": 18,
  "config": {
    "seed": 1,
    "gamma": 0.3,
    "margin": 0.02,
    "delta": 0.02,
    "input_vmin": 0.0,
    "input_vmax": 1.0,
    "rails": [
      0.0,
      0.45
    ],
    "solver": "klu",
    "body_tie": "floating",
    "body_res": 10.0,
    "rs_clamp": 10.0,
    "model_vto": 0.75,
    "vg_cutoff": 0.75,
    "vg_cutoff_epochs": 4,
    "vg_init": {
      "mode": "random",
      "lo": 1.0,
      "hi": 6.0,
      "fixed": 2.0
    },
    "epochs": 100,
    "device_include_path": "/home/ma-lab/Desktop/pyclln-final/device_model/nmos_lvl1_ald1106.lib",
    "device_subckt": "NMOSWRAP"
  },
  "train": {
    "acc": 0.8538622129436325,
    "hinge": 0.008044635421015993,
    "n_free": 1437,
    "n_clamp": 781,
    "hinge_active": 781,
    "hinge_active_frac": 0.5434933890048712,
    "skipped": 656,
    "reload_free": 0,
    "reload_clamp": 0,
    "nonfinite_free": 0,
    "nonfinite_clamp": 0
  },
  "val": {
    "acc": 0.8611111111111112,
    "hinge": 0.007373345833333332,
    "test_gap_mean": 0.016519063055555557,
    "test_gap_median": 0.01835340000000002,
    "test_gap_std": 0.014117211363033132,
    "test_satisfy_frac": 0.46111111111111114,
    "test_hinge_mean": 0.007373345833333334,
    "val_reloads": 0.0,
    "val_nonfinite": 0.0
  },
  "timing_s": {
    "epoch_total": 251.0015902519226,
    "train_free": 134.8099341392517,
    "train_clamp": 72.96687841415405,
    "train_update": 2.290660858154297
  },
  "vg_stats": {
    "vg_unique_min": 0.6283123799488697,
    "vg_unique_max": 6.883287311119774,
    "vg_unique_sat_lo": 0.0,
    "vg_unique_sat_hi": 0.0
  }
}