{
  "epoch": 43,
  "config": {
    "seed": 2,
    "gamma": 0.3,
    "margin": 0.02,
    "delta": 0.1,
    "input_vmin": 0.0,
    "input_vmax": 1.0,
    "rails": [
      0.0,
      0.45
    ],
    "solver": "klu",
    "body_tie": "source",
    "body_res": 10.0,
    "rs_clamp": 10.0,
    "model_vto": 0.75,
    "vg_cutoff": 0.75,
    "vg_cutoff_epochs": 4,
    "vg_init": {
      "mode": "random",
      "lo": 1.0,
      "hi": 6.0,
      "fixed": 2.0
    },
    "epochs": 100,
    "device_include_path": "/home/ma-lab/Desktop/pyclln-final/device_model/nmos_lvl1_ald1106.lib",
    "device_subckt": "NMOSWRAP"
  },
  "train": {
    "acc": 0.9742519137091162,
    "hinge": 0.0016218871955462754,
    "n_free": 1437,
    "n_clamp": 200,
    "hinge_active": 200,
    "hinge_active_frac": 0.13917884481558804,
    "skipped": 1237,
    "reload_free": 0,
    "reload_clamp": 0,
    "nonfinite_free": 0,
    "nonfinite_clamp": 0
  },
  "val": {
    "acc": 0.95,
    "hinge": 0.0029917491666666667,
    "test_gap_mean": 0.03579075944444444,
    "test_gap_median": 0.037985450000000004,
    "test_gap_std": 0.020570713253053607,
    "test_satisfy_frac": 0.7833333333333333,
    "test_hinge_mean": 0.002991749166666667,
    "val_reloads": 0.0,
    "val_nonfinite": 0.0
  },
  "timing_s": {
    "epoch_total": 64.62223958969116,
    "train_free": 41.201701402664185,
    "train_clamp": 5.703131914138794,
    "train_update": 0.531121015548706
  },
  "vg_stats": {
    "vg_unique_min": 0.6565402154944661,
    "vg_unique_max": 8.0,
    "vg_unique_sat_lo": 0.0,
    "vg_unique_sat_hi": 1.0
  }
}