{
  "epoch": 45,
  "config": {
    "seed": 1,
    "gamma": 0.3,
    "margin": 0.02,
    "delta": 0.1,
    "input_vmin": 0.0,
    "input_vmax": 1.0,
    "rails": [
      0.0,
      0.45
    ],
    "solver": "klu",
    "body_tie": "floating",
    "body_res": 10.0,
    "rs_clamp": 10.0,
    "model_vto": 0.75,
    "vg_cutoff": 0.75,
    "vg_cutoff_epochs": 4,
    "vg_init": {
      "mode": "fixed",
      "lo": 1.0,
      "hi": 3.0,
      "fixed": 2.0
    },
    "epochs": 100,
    "device_include_path": "/home/ma-lab/Desktop/pyclln-final/device_model/nmos_lvl1_ald1106.lib",
    "device_subckt": "NMOSWRAP"
  },
  "train": {
    "acc": 0.97633959638135,
    "hinge": 0.001308335699373694,
    "n_free": 1437,
    "n_clamp": 127,
    "hinge_active": 127,
    "hinge_active_frac": 0.0883785664578984,
    "skipped": 1310,
    "reload_free": 0,
    "reload_clamp": 0,
    "nonfinite_free": 0,
    "nonfinite_clamp": 0
  },
  "val": {
    "acc": 0.9444444444444444,
    "hinge": 0.0024974850000000007,
    "test_gap_mean": 0.05303113416666666,
    "test_gap_median": 0.056094050000000006,
    "test_gap_std": 0.02945571356473655,
    "test_satisfy_frac": 0.8666666666666667,
    "test_hinge_mean": 0.0024974850000000007,
    "val_reloads": 0.0,
    "val_nonfinite": 0.0
  },
  "timing_s": {
    "epoch_total": 106.56915187835693,
    "train_free": 76.13050150871277,
    "train_clamp": 6.878268003463745,
    "train_update": 0.3019235134124756
  },
  "vg_stats": {
    "vg_unique_min": 0.6630904892824034,
    "vg_unique_max": 3.7284292350349175,
    "vg_unique_sat_lo": 0.0,
    "vg_unique_sat_hi": 0.0
  }
}