{
  "epoch": 2,
  "config": {
    "seed": 2,
    "gamma": 3.0,
    "margin": 0.05,
    "delta": 0.1,
    "input_vmin": 0.0,
    "input_vmax": 1.0,
    "rails": [
      0.0,
      0.45
    ],
    "solver": "klu",
    "body_tie": "floating",
    "body_res": 10.0,
    "rs_clamp": 10.0,
    "model_vto": 0.75,
    "vg_cutoff": 0.75,
    "vg_cutoff_epochs": 4,
    "vg_init": {
      "mode": "random",
      "lo": 0.75,
      "hi": 3.0,
      "fixed": 2.0
    },
    "epochs": 100,
    "device_include_path": "/home/ma-lab/Desktop/pyclln-final/device_model/nmos_lvl1_ald1106.lib",
    "device_subckt": "NMOSWRAP"
  },
  "train": {
    "acc": 0.9206680584551148,
    "hinge": 0.010222615588030623,
    "n_free": 1437,
    "n_clamp": 363,
    "hinge_active": 363,
    "hinge_active_frac": 0.25260960334029225,
    "skipped": 1074,
    "reload_free": 0,
    "reload_clamp": 0,
    "nonfinite_free": 0,
    "nonfinite_clamp": 0
  },
  "val": {
    "acc": 0.925,
    "hinge": 0.011465266666666673,
    "test_gap_mean": 0.08670773861111111,
    "test_gap_median": 0.0899942,
    "test_gap_std": 0.06339610331859946,
    "test_satisfy_frac": 0.7305555555555555,
    "test_hinge_mean": 0.011465266666666666,
    "val_reloads": 0.0,
    "val_nonfinite": 0.0
  },
  "timing_s": {
    "epoch_total": 79.83206057548523,
    "train_free": 49.80378031730652,
    "train_clamp": 12.499678134918213,
    "train_update": 0.7764079570770264
  },
  "vg_stats": {
    "vg_unique_min": 0.4,
    "vg_unique_max": 5.746938429714413,
    "vg_unique_sat_lo": 42.0,
    "vg_unique_sat_hi": 0.0
  }
}